MANIFEST.in
README.rst
setup.py
wafflehaus/__init__.py
wafflehaus/base.py
wafflehaus.egg-info/PKG-INFO
wafflehaus.egg-info/SOURCES.txt
wafflehaus.egg-info/dependency_links.txt
wafflehaus.egg-info/namespace_packages.txt
wafflehaus.egg-info/not-zip-safe
wafflehaus.egg-info/pbr.json
wafflehaus.egg-info/requires.txt
wafflehaus.egg-info/top_level.txt
wafflehaus/dns_filter/__init__.py
wafflehaus/dns_filter/whitelist.py
wafflehaus/edit_response/__init__.py
wafflehaus/log_filters/__init__.py
wafflehaus/log_filters/req_resp.py
wafflehaus/payload_filter/__init__.py
wafflehaus/payload_filter/unset_key.py
wafflehaus/resource_filter/__init__.py
wafflehaus/resource_filter/alias.py
wafflehaus/resource_filter/block_resource.py
wafflehaus/routers/__init__.py
wafflehaus/routers/rolerouter.py
wafflehaus/tests/__init__.py
wafflehaus/tests/test_dns_filter.py
wafflehaus/tests/test_edit_response.py
wafflehaus/tests/test_payload_filter.py
wafflehaus/tests/test_resource_alias.py
wafflehaus/tests/test_resource_filter.py
wafflehaus/tests/test_rolerouter.py
wafflehaus/tests/test_try_context.py
wafflehaus/tests/test_wafflehaus_base.py
wafflehaus/try_context/__init__.py
wafflehaus/try_context/context_filter.py